CHANGES.md
LICENSE
MANIFEST.in
README.md
requirements.txt
setup.py
Lector.egg-info/PKG-INFO
Lector.egg-info/SOURCES.txt
Lector.egg-info/dependency_links.txt
Lector.egg-info/requires.txt
Lector.egg-info/top_level.txt
lector/__init__.py
lector/api.py
lector/reader.py