Metadata-Version: 1.0
Name: Lector
Version: 0.0.3
Summary: An API for Amazon Kindle Data
Home-page: https://github.com/msuozzo/Lector
Author: Matthew Suozzo
Author-email: iratus.litteris@gmail.com
License: MIT
Platform: UNKNOWN
